LICENSE
pynpc/__init__.py
pynpc/console.py
pynpc/data/archetypes.res.json
pynpc/data/archetypes.txt
pynpc/data/cards.res.json
pynpc/data/fantasy-professions.res.json
pynpc/data/fantasy-professions.txt
pynpc/data/idiosyncrasies.res.json
pynpc/data/idiosyncrasies.txt
pynpc/data/name-corruption-pattern.json
pynpc/data/personalities.res.json
pynpc/data/phobia.res.json
pynpc/data/phobia.txt
pynpc/name_corruptor.py
pynpc/npc.py
pynpc/skills.py
pynpc/utils.py
pynpc-0.4.0.dist-info/LICENSE
pynpc-0.4.0.dist-info/METADATA
pynpc-0.4.0.dist-info/WHEEL
pynpc-0.4.0.dist-info/entry_points.txt
pynpc-0.4.0.dist-info/RECORD
