Metadata-Version: 2.1
Name: pynpc
Version: 0.4.0
Summary: Generate simple NPCs for table top role playing games
Home-page: https://github.com/kierun/pynpc
License: MIT
Keywords: ttrpg,rpg,generate,NPC
Author: Dr Yann Golanski
Author-email: github@kierun.org
Requires-Python: >=3.10,<4.0
Classifier: License :: OSI Approved :: MIT License
Classifier: Programming Language :: Python :: 3
Classifier: Programming Language :: Python :: 3.10
Classifier: Programming Language :: Python :: 3.11
Classifier: Programming Language :: Python :: 3.12
Classifier: Programming Language :: Python :: 3.13
Requires-Dist: click (>=8.1.8,<9.0.0)
Requires-Dist: click-help-colors (>=0.9.4,<0.10.0)
Requires-Dist: mimesis (>=14.0.0,<15.0.0)
Requires-Dist: orjson (>=3.10.15,<4.0.0)
Requires-Dist: pendulum (>=3.0.0,<4.0.0)
Requires-Dist: requests (>=2.32.3,<3.0.0)
Requires-Dist: rich (>=13.9.4,<14.0.0)
Requires-Dist: structlog (>=23.3,<25.0)
Requires-Dist: typer-config[all] (>=1.4.2,<2.0.0)
Requires-Dist: typer[all] (>=0.9.0,<0.10.0)
Requires-Dist: types-requests (>=2.32.0.20250306,<3.0.0.0)
Requires-Dist: unidecode (>=1.3.8,<2.0.0)
Project-URL: Repository, https://github.com/kierun/pynpc
